custom_onnx/__init__.py
custom_onnx/_frontend.py
custom_onnx/_version.py
custom_onnx/example.py
custom_onnx/labextension/install.json
custom_onnx/labextension/package.json
custom_onnx/labextension/static/120.c5a553dc40cba5df79c6.js
custom_onnx/labextension/static/480.2aee3b9f6b2de3a7793b.js
custom_onnx/labextension/static/568.8cbbabd8199f25d8e8d8.js
custom_onnx/labextension/static/736.a60a98948f97f7dc8b7b.js
custom_onnx/labextension/static/736.a60a98948f97f7dc8b7b.js.LICENSE.txt
custom_onnx/labextension/static/861.41b58f7a96c73fa6f914.js
custom_onnx/labextension/static/861.41b58f7a96c73fa6f914.js.LICENSE.txt
custom_onnx/labextension/static/remoteEntry.aa2866118452cb4b32fe.js
custom_onnx/labextension/static/style.js
custom_onnx/labextension/static/third-party-licenses.json
custom_onnx/nbextension/extension.js
custom_onnx/nbextension/index.js
custom_onnx/nbextension/index.js.LICENSE.txt
custom_onnx/nbextension/index.js.map
custom_onnx/nbextension/ort-wasm-simd-threaded.wasm
custom_onnx/nbextension/ort-wasm-simd.wasm
custom_onnx/nbextension/ort-wasm-threaded.wasm
custom_onnx/nbextension/ort-wasm.wasm
custom_onnx/tests/__init__.py
custom_onnx/tests/conftest.py
custom_onnx/tests/test_example.py
custom_onnx/tests/test_nbextension_path.py
custom_onnx-0.1.1.data/data/share/jupyter/labextensions/custom_onnx/install.json
custom_onnx-0.1.1.data/data/share/jupyter/labextensions/custom_onnx/package.json
custom_onnx-0.1.1.data/data/share/jupyter/labextensions/custom_onnx/static/120.c5a553dc40cba5df79c6.js
custom_onnx-0.1.1.data/data/share/jupyter/labextensions/custom_onnx/static/480.2aee3b9f6b2de3a7793b.js
custom_onnx-0.1.1.data/data/share/jupyter/labextensions/custom_onnx/static/568.8cbbabd8199f25d8e8d8.js
custom_onnx-0.1.1.data/data/share/jupyter/labextensions/custom_onnx/static/736.a60a98948f97f7dc8b7b.js
custom_onnx-0.1.1.data/data/share/jupyter/labextensions/custom_onnx/static/736.a60a98948f97f7dc8b7b.js.LICENSE.txt
custom_onnx-0.1.1.dist-info/METADATA
custom_onnx-0.1.1.dist-info/WHEEL
custom_onnx-0.1.1.dist-info/licenses/LICENSE.txt
custom_onnx-0.1.1.dist-info/RECORD
